llmasp/__init__.py
llmasp/asp/__init__.py
llmasp/asp/solver.py
llmasp/llm/__init__.py
llmasp/llm/abstract_llmasp.py
llmasp/llm/llm_handler.py
llmasp/llm/llmasp.py
llmasp-0.1.8.dist-info/LICENSE
llmasp-0.1.8.dist-info/METADATA
llmasp-0.1.8.dist-info/WHEEL
llmasp-0.1.8.dist-info/RECORD
