Metadata-Version: 2.1
Name: llmasp
Version: 0.1.8
Summary: Combining LLMs and ASP for intelligent problem-solving and reasoning.
Author: Luis Angel
Author-email: luis.rodriguezreiners@gmail.com
Requires-Python: >=3.12,<4.0
Classifier: Programming Language :: Python :: 3
Classifier: Programming Language :: Python :: 3.12
Requires-Dist: dumbo-asp (>=0.3.8,<0.4.0)
Requires-Dist: openai (>=1.35.5,<2.0.0)
Requires-Dist: pyyaml (>=6.0.1,<7.0.0)
